odoo/addons/base_report_to_label_printer/README.rst
odoo/addons/base_report_to_label_printer/__init__.py
odoo/addons/base_report_to_label_printer/__manifest__.py
odoo/addons/base_report_to_label_printer/i18n/base_report_to_label_printer.pot
odoo/addons/base_report_to_label_printer/i18n/fr.po
odoo/addons/base_report_to_label_printer/i18n/it.po
odoo/addons/base_report_to_label_printer/models/__init__.py
odoo/addons/base_report_to_label_printer/models/ir_actions_report.py
odoo/addons/base_report_to_label_printer/models/res_users.py
odoo/addons/base_report_to_label_printer/readme/CONTRIBUTORS.md
odoo/addons/base_report_to_label_printer/readme/CREDITS.md
odoo/addons/base_report_to_label_printer/readme/DESCRIPTION.md
odoo/addons/base_report_to_label_printer/static/description/icon.png
odoo/addons/base_report_to_label_printer/static/description/index.html
odoo/addons/base_report_to_label_printer/tests/__init__.py
odoo/addons/base_report_to_label_printer/tests/test_ir_actions_report.py
odoo/addons/base_report_to_label_printer/views/ir_actions_report.xml
odoo/addons/base_report_to_label_printer/views/res_users.xml
odoo_addon_base_report_to_label_printer-18.0.1.0.1.dist-info/METADATA
odoo_addon_base_report_to_label_printer-18.0.1.0.1.dist-info/WHEEL
odoo_addon_base_report_to_label_printer-18.0.1.0.1.dist-info/top_level.txt
odoo_addon_base_report_to_label_printer-18.0.1.0.1.dist-info/RECORD
