Metadata-Version: 2.1
Name: odoo-addon-base_report_to_label_printer
Version: 18.0.1.0.1
Requires-Python: >=3.10
Requires-Dist: odoo-addon-base_report_to_printer==18.0.*
Requires-Dist: odoo==18.0.*
Summary: Report to label printer
Home-page: https://github.com/OCA/report-print-send
License: AGPL-3
Author: Raumschmiede GmbH - Christopher Hansen, Odoo Community Association (OCA)
Author-email: support@odoo-community.org
Classifier: Programming Language :: Python
Classifier: Framework :: Odoo
Classifier: Framework :: Odoo :: 18.0
Classifier: License :: OSI Approved :: GNU Affero General Public License v3
